AUTHORS.rst
CONTRIBUTING.rst
HISTORY.rst
LICENSE
MANIFEST.in
README.rst
setup.cfg
setup.py
docs/Makefile
docs/authors.rst
docs/conf.py
docs/contributing.rst
docs/history.rst
docs/index.rst
docs/installation.rst
docs/make.bat
docs/readme.rst
docs/usage.rst
payzone/__init__.py
payzone/client.py
payzone/exceptions.py
payzone.egg-info/PKG-INFO
payzone.egg-info/SOURCES.txt
payzone.egg-info/dependency_links.txt
payzone.egg-info/not-zip-safe
payzone.egg-info/requires.txt
payzone.egg-info/top_level.txt
tests/__init__.py