Metadata-Version: 1.1
Name: payzone
Version: 0.1.1
Summary: Python package for payment gateway Payzone
Home-page: https://github.com/kamotos/payzone
Author: Zahim Anass
Author-email: zanass0@gmail.com
License: BSD
Keywords: payzone
Platform: UNKNOWN
Classifier: Development Status :: 2 - Pre-Alpha
Classifier: Intended Audience :: Developers
Classifier: License :: OSI Approved :: BSD License
Classifier: Natural Language :: English
Classifier: Programming Language :: Python :: 2
Classifier: Programming Language :: Python :: 2.6
Classifier: Programming Language :: Python :: 2.7
Classifier: Programming Language :: Python :: 3
Classifier: Programming Language :: Python :: 3.3
Classifier: Programming Language :: Python :: 3.4
